macadam/__init__.py
macadam/base/__init__.py
macadam/base/embedding.py
macadam/base/graph.py
macadam/base/layers.py
macadam/base/preprocess.py
macadam/base/utils.py
macadam/conf/__init__.py
macadam/conf/constant_params.py
macadam/conf/logger_config.py
macadam/conf/path_config.py
macadam/data/__init__.py
macadam/data/corpus/__init__.py
macadam/data/corpus/sequence_labeling/__init__.py
macadam/data/corpus/text_classification/__init__.py
macadam/data/corpus/text_classification/baidu_qa_2019/__init__.py
macadam/data/corpus/text_classification/baidu_qa_2019_small/__init__.py
macadam/data/corpus/text_classification/medicine/__init__.py
macadam/data/embed/__init__.py
macadam/data/embed/chinese_L-12_H-768_A-12/__init__.py
macadam/data/model/__init__.py
macadam/joint/__init__.py
macadam/re/__init__.py
macadam/sl/__init__.py
macadam/sl/s00_map.py
macadam/sl/s00_predict.py
macadam/sl/s00_trainer.py
macadam/sl/s01_crf.py
macadam/sl/s02_bilstm_crf.py
macadam/sl/s03_cnn_lstm.py
macadam/sl/s04_dgcnn.py
macadam/sl/s05_bilstm_lan.py
macadam/sl/s06_lattice_lstm_batch.py
macadam/sl/s07_mrc.py
macadam/tc/__init__.py
macadam/tc/t00_map.py
macadam/tc/t00_predict.py
macadam/tc/t00_trainer.py
macadam/tc/t01_finetune.py
macadam/tc/t02_fasttext.py
macadam/tc/t03_textcnn.py
macadam/tc/t04_charcnn.py
macadam/tc/t05_birnn.py
macadam/tc/t06_rcnn.py
macadam/tc/t07_dcnn.py
macadam/tc/t08_crnn.py
macadam/tc/t09_deepmoji.py
macadam/tc/t10_attention.py
macadam/tc/t11_capsule.py
test/__init__.py
test/compare/__init__.py
test/corpus/__init__.py
test/corpus/create_ner.py
test/corpus/create_tc.py
test/corpus/ner_clue_to_macadam.py
test/docs/__init__.py
test/embedding/__init__.py
test/embedding/tet_albert.py
test/embedding/tet_bert.py
test/embedding/tet_electra.py
test/embedding/tet_mix.py
test/embedding/tet_nezha.py
test/embedding/tet_random.py
test/embedding/tet_roberta.py
test/embedding/tet_word2vec.py
test/embedding/tet_xlnet.py
test/images/__init__.py
test/preprocess/__init__.py
Macadam-0.1.1.dist-info/LICENSE
Macadam-0.1.1.dist-info/METADATA
Macadam-0.1.1.dist-info/WHEEL
Macadam-0.1.1.dist-info/top_level.txt
Macadam-0.1.1.dist-info/RECORD
