Metadata-Version: 2.1
Name: Macadam
Version: 0.1.1
Summary: Joint-NER-and-RE
Home-page: https://github.com/yongzhuo/Macadam
Author: yongzhuo
Author-email: 1903865025@qq.com
License: MIT
Requires-Dist: keras-xlnet (==0.18.0)
Requires-Dist: bert4keras (==0.7.0)
Requires-Dist: macropodus (==0.0.6)
Requires-Dist: tqdm (==4.31.1)
